MANIFEST.in
README.rst
setup.cfg
setup.py
conlog/ConLog.py
conlog/__init__.py
conlog.egg-info/PKG-INFO
conlog.egg-info/SOURCES.txt
conlog.egg-info/dependency_links.txt
conlog.egg-info/requires.txt
conlog.egg-info/top_level.txt
test/test_from_args.py
test/test_from_yaml.py
test/test_other.py