Metadata-Version: 1.1
Name: conlog
Version: 1.1.3
Summary: Anti-Boilerplate Console Logging Module for Python
Home-page: https://github.com/RyanMillerC/conlog
Author: Ryan Miller
Author-email: ryan@devopsmachine.com
License: MIT
Download-URL: https://github.com/RyanMillerC/conlog/archive/1.1.3.tar.gz
Keywords: logging,debugging
Platform: UNKNOWN
Classifier: Intended Audience :: Developers
Classifier: License :: OSI Approved :: MIT License
Classifier: Operating System :: OS Independent
Classifier: Programming Language :: Python :: 2
Classifier: Programming Language :: Python :: 3
Classifier: Topic :: System :: Logging
